kwik/__init__.py
kwik/__main__.py
kwik/database.py
kwik/logging.py
kwik/routers.py
kwik/security.py
kwik/settings.py
kwik/api/__init__.py
kwik/api/api.py
kwik/api/endpoints/__init__.py
kwik/api/endpoints/login.py
kwik/api/endpoints/permissions.py
kwik/api/endpoints/roles.py
kwik/api/endpoints/users.py
kwik/applications/__init__.py
kwik/applications/gunicorn.py
kwik/applications/kwik.py
kwik/applications/run.py
kwik/applications/uvicorn.py
kwik/core/__init__.py
kwik/core/enum.py
kwik/crud/__init__.py
kwik/crud/autocrud.py
kwik/crud/context.py
kwik/crud/permissions.py
kwik/crud/roles.py
kwik/crud/users.py
kwik/dependencies/__init__.py
kwik/dependencies/context.py
kwik/dependencies/filter_query.py
kwik/dependencies/list_query.py
kwik/dependencies/pagination.py
kwik/dependencies/permissions.py
kwik/dependencies/session.py
kwik/dependencies/settings.py
kwik/dependencies/sorting_query.py
kwik/dependencies/token.py
kwik/dependencies/users.py
kwik/exceptions/__init__.py
kwik/exceptions/base.py
kwik/exceptions/handler.py
kwik/exceptions/users.py
kwik/models/__init__.py
kwik/models/base.py
kwik/models/mixins.py
kwik/models/user.py
kwik/schemas/__init__.py
kwik/schemas/mixins.py
kwik/schemas/pagination.py
kwik/schemas/permission.py
kwik/schemas/role.py
kwik/schemas/token.py
kwik/schemas/user.py
kwik/testing/__init__.py
kwik/testing/client.py
kwik/testing/scenario.py
kwik/testing/fixtures/__init__.py
kwik/testing/fixtures/core_fixtures.py
kwik/testing/fixtures/factories.py
kwik/utils/__init__.py
kwik/utils/files.py
kwik-1.3.2.dist-info/METADATA
kwik-1.3.2.dist-info/WHEEL
kwik-1.3.2.dist-info/entry_points.txt
kwik-1.3.2.dist-info/licenses/LICENSE
kwik-1.3.2.dist-info/RECORD
