Metadata-Version: 2.4
Name: kwik
Version: 1.3.2
Summary: Fast, batteries-included, business-oriented, opinionated REST APIs framework
Author-email: dmezzogori <dmezzogori@users.noreply.github.com>
License-File: LICENSE
Requires-Python: >=3.12
Requires-Dist: aiofiles==24.1.0
Requires-Dist: bcrypt==4.0.1
Requires-Dist: fastapi[standard]==0.116.1
Requires-Dist: gunicorn==23.0.0
Requires-Dist: httptools==0.6.4
Requires-Dist: loguru>=0.7.3
Requires-Dist: psycopg2-binary==2.9.10
Requires-Dist: pydantic-settings>=2.10.1
Requires-Dist: pydantic[email]<3.0.0,>=2.0.0
Requires-Dist: pyjwt>=2.10.0
Requires-Dist: pytest>=8.0.0
Requires-Dist: sqlalchemy<3.0.0,>=2.0.0
Requires-Dist: testcontainers>=4.0.0
